setup.py
shinkenplugins/__init__.py
shinkenplugins.plugins.drupal_views.egg-info/PKG-INFO
shinkenplugins.plugins.drupal_views.egg-info/SOURCES.txt
shinkenplugins.plugins.drupal_views.egg-info/dependency_links.txt
shinkenplugins.plugins.drupal_views.egg-info/entry_points.txt
shinkenplugins.plugins.drupal_views.egg-info/namespace_packages.txt
shinkenplugins.plugins.drupal_views.egg-info/requires.txt
shinkenplugins.plugins.drupal_views.egg-info/top_level.txt
shinkenplugins/plugins/__init__.py
shinkenplugins/plugins/drupal_views/__init__.py
shinkenplugins/plugins/drupal_views/drupal_views.py